{
  "externalPackages": [
    "@clerk",
    "@hookform",
    "@prisma",
    "clsx",
    "dotenv",
    "framer-motion",
    "lucide-react",
    "next",
    "prisma",
    "react",
    "react-hook-form",
    "svix",
    "tailwind-merge",
    "zod",
    "zustand"
  ],
  "unusedDeps": [
    "@clerk/nextjs",
    "@hookform/resolvers",
    "@prisma/adapter-pg",
    "@prisma/client",
    "class-variance-authority",
    "pg",
    "react-dom",
    "recharts",
    "@tailwindcss/postcss",
    "@types/node",
    "@types/pg",
    "@types/react",
    "@types/react-dom",
    "eslint",
    "eslint-config-next",
    "tailwindcss",
    "typescript"
  ],
  "unreferenced": [
    "next-env.d.ts",
    "proxy.ts"
  ],
  "routeFiles": [
    "app/(auth)/login/page.tsx",
    "app/(auth)/signup/page.tsx",
    "app/(marketing)/page.tsx",
    "app/api/webhooks/clerk/route.ts",
    "app/auth-callback/page.tsx",
    "app/dashboard/career/page.tsx",
    "app/dashboard/github/page.tsx",
    "app/dashboard/layout.tsx",
    "app/dashboard/mentor/page.tsx",
    "app/dashboard/page.tsx",
    "app/dashboard/projects/page.tsx",
    "app/dashboard/projects/[id]/page.tsx",
    "app/dashboard/roadmaps/page.tsx",
    "app/dashboard/settings/page.tsx",
    "app/layout.tsx",
    "app/onboarding/page.tsx"
  ],
  "fileRefs": {
    "app/(auth)/login/page.tsx": 0,
    "components/ui/BrandIcons.tsx": 0,
    "store/useAppStore.ts": 0,
    "components/ui/Button.tsx": 0,
    "components/ui/Input.tsx": 0,
    "components/ui/Card.tsx": 0,
    "app/(auth)/signup/page.tsx": 0,
    "app/(marketing)/page.tsx": 0,
    "components/layout/Navbar.tsx": 0,
    "components/ui/Badge.tsx": 0,
    "app/actions/user.ts": 2,
    "lib/prisma.ts": 1,
    "app/api/webhooks/clerk/route.ts": 0,
    "lib/userSync.ts": 0,
    "app/auth-callback/page.tsx": 0,
    "app/dashboard/career/page.tsx": 0,
    "components/ui/Progress.tsx": 0,
    "app/dashboard/github/page.tsx": 0,
    "app/dashboard/layout.tsx": 0,
    "components/layout/Sidebar.tsx": 0,
    "app/dashboard/mentor/page.tsx": 0,
    "app/dashboard/page.tsx": 0,
    "app/dashboard/projects/page.tsx": 0,
    "app/dashboard/projects/[id]/page.tsx": 0,
    "app/dashboard/roadmaps/page.tsx": 0,
    "app/dashboard/settings/page.tsx": 0,
    "app/layout.tsx": 0,
    "app/onboarding/page.tsx": 0,
    "components/ui/UploadZone.tsx": 0,
    "lib/utils.ts": 0,
    "lib/adaptiveEngine.ts": 1,
    "types/index.ts": 0,
    "lib/mockAiEngine.ts": 1,
    "next-env.d.ts": 0,
    "next.config.ts": 0,
    "prisma.config.ts": 0,
    "proxy.ts": 0
  },
  "exports": {
    "app/(auth)/login/page.tsx": [
      "LoginPage",
      "default:LoginPage"
    ],
    "app/(auth)/signup/page.tsx": [
      "SignupPage",
      "default:SignupPage"
    ],
    "app/(marketing)/page.tsx": [
      "MarketingPage",
      "default:MarketingPage"
    ],
    "app/actions/user.ts": [
      "OnboardingPayload",
      "async"
    ],
    "app/api/webhooks/clerk/route.ts": [
      "runtime",
      "async"
    ],
    "app/auth-callback/page.tsx": [
      "dynamic",
      "async",
      "default:async"
    ],
    "app/dashboard/career/page.tsx": [
      "CareerScorePage",
      "default:CareerScorePage"
    ],
    "app/dashboard/github/page.tsx": [
      "GitHubAnalyticsPage",
      "default:GitHubAnalyticsPage"
    ],
    "app/dashboard/layout.tsx": [
      "DashboardLayout",
      "default:DashboardLayout"
    ],
    "app/dashboard/mentor/page.tsx": [
      "AiMentorChatPage",
      "default:AiMentorChatPage"
    ],
    "app/dashboard/page.tsx": [
      "MainDashboardPage",
      "default:MainDashboardPage"
    ],
    "app/dashboard/projects/page.tsx": [
      "RecommendedProjectsPage",
      "default:RecommendedProjectsPage"
    ],
    "app/dashboard/projects/[id]/page.tsx": [
      "ProjectDetailsPage",
      "default:ProjectDetailsPage"
    ],
    "app/dashboard/roadmaps/page.tsx": [
      "VisualRoadmapsPage",
      "default:VisualRoadmapsPage"
    ],
    "app/dashboard/settings/page.tsx": [
      "SettingsPage",
      "default:SettingsPage"
    ],
    "app/layout.tsx": [
      "metadata",
      "RootLayout",
      "default:RootLayout"
    ],
    "app/onboarding/page.tsx": [
      "OnboardingPage",
      "default:OnboardingPage"
    ],
    "components/layout/Navbar.tsx": [
      "Navbar"
    ],
    "components/layout/Sidebar.tsx": [
      "Sidebar"
    ],
    "components/ui/Badge.tsx": [
      "BadgeProps",
      "Badge"
    ],
    "components/ui/BrandIcons.tsx": [
      "IconProps",
      "Github",
      "Linkedin",
      "Chrome"
    ],
    "components/ui/Button.tsx": [
      "ButtonProps",
      "Button"
    ],
    "components/ui/Card.tsx": [
      "CardProps",
      "Card",
      "CardHeader",
      "CardTitle",
      "CardDescription",
      "CardContent",
      "CardFooter"
    ],
    "components/ui/Input.tsx": [
      "InputProps",
      "Input"
    ],
    "components/ui/Progress.tsx": [
      "ProgressProps",
      "Progress"
    ],
    "components/ui/UploadZone.tsx": [
      "UploadZoneProps",
      "UploadZone"
    ],
    "lib/adaptiveEngine.ts": [
      "generateAdaptiveDashboard"
    ],
    "lib/mockAiEngine.ts": [
      "generateSmartReply"
    ],
    "lib/prisma.ts": [
      "prisma"
    ],
    "lib/userSync.ts": [
      "ClerkUserParam",
      "async"
    ],
    "lib/utils.ts": [
      "cn"
    ],
    "next-env.d.ts": [],
    "next.config.ts": [
      "nextConfig",
      "default:nextConfig"
    ],
    "prisma.config.ts": [
      "defineConfig",
      "default:defineConfig"
    ],
    "proxy.ts": [
      "proxy",
      "config",
      "default:proxy"
    ],
    "store/useAppStore.ts": [
      "AgentConnector",
      "useAppStore"
    ],
    "types/index.ts": [
      "User",
      "OnboardingData",
      "Project",
      "RoadmapStep",
      "Roadmap",
      "ChatMessage",
      "ChatConversation",
      "CommitActivity",
      "LanguageBreakdown",
      "RepositoryIntelligence",
      "GitHubAnalytics",
      "CareerScore"
    ]
  },
  "unusedExports": [
    "app/(auth)/login/page.tsx::LoginPage",
    "app/(auth)/login/page.tsx::default:LoginPage",
    "app/(auth)/signup/page.tsx::SignupPage",
    "app/(auth)/signup/page.tsx::default:SignupPage",
    "app/(marketing)/page.tsx::MarketingPage",
    "app/(marketing)/page.tsx::default:MarketingPage",
    "app/actions/user.ts::OnboardingPayload",
    "app/actions/user.ts::async",
    "app/api/webhooks/clerk/route.ts::runtime",
    "app/api/webhooks/clerk/route.ts::async",
    "app/auth-callback/page.tsx::dynamic",
    "app/auth-callback/page.tsx::async",
    "app/auth-callback/page.tsx::default:async",
    "app/dashboard/career/page.tsx::CareerScorePage",
    "app/dashboard/career/page.tsx::default:CareerScorePage",
    "app/dashboard/github/page.tsx::GitHubAnalyticsPage",
    "app/dashboard/github/page.tsx::default:GitHubAnalyticsPage",
    "app/dashboard/layout.tsx::DashboardLayout",
    "app/dashboard/layout.tsx::default:DashboardLayout",
    "app/dashboard/mentor/page.tsx::AiMentorChatPage",
    "app/dashboard/mentor/page.tsx::default:AiMentorChatPage",
    "app/dashboard/page.tsx::MainDashboardPage",
    "app/dashboard/page.tsx::default:MainDashboardPage",
    "app/dashboard/projects/page.tsx::RecommendedProjectsPage",
    "app/dashboard/projects/page.tsx::default:RecommendedProjectsPage",
    "app/dashboard/projects/[id]/page.tsx::ProjectDetailsPage",
    "app/dashboard/projects/[id]/page.tsx::default:ProjectDetailsPage",
    "app/dashboard/roadmaps/page.tsx::VisualRoadmapsPage",
    "app/dashboard/roadmaps/page.tsx::default:VisualRoadmapsPage",
    "app/dashboard/settings/page.tsx::SettingsPage",
    "app/dashboard/settings/page.tsx::default:SettingsPage",
    "app/layout.tsx::metadata",
    "app/layout.tsx::RootLayout",
    "app/layout.tsx::default:RootLayout",
    "app/onboarding/page.tsx::OnboardingPage",
    "app/onboarding/page.tsx::default:OnboardingPage",
    "components/ui/Badge.tsx::BadgeProps",
    "components/ui/BrandIcons.tsx::IconProps",
    "components/ui/Button.tsx::ButtonProps",
    "components/ui/Card.tsx::CardProps",
    "components/ui/Input.tsx::InputProps",
    "components/ui/Progress.tsx::ProgressProps",
    "components/ui/UploadZone.tsx::UploadZoneProps",
    "lib/userSync.ts::ClerkUserParam",
    "lib/userSync.ts::async",
    "next.config.ts::nextConfig",
    "next.config.ts::default:nextConfig",
    "prisma.config.ts::defineConfig",
    "prisma.config.ts::default:defineConfig",
    "proxy.ts::proxy",
    "proxy.ts::config",
    "proxy.ts::default:proxy",
    "store/useAppStore.ts::AgentConnector",
    "types/index.ts::OnboardingData",
    "types/index.ts::RoadmapStep",
    "types/index.ts::Roadmap",
    "types/index.ts::ChatConversation",
    "types/index.ts::CommitActivity",
    "types/index.ts::LanguageBreakdown",
    "types/index.ts::RepositoryIntelligence",
    "types/index.ts::GitHubAnalytics"
  ]
}